{
  "title": "Nhóm MTV hát 'Thanh Niên Ca' mừng sinh nhật 40 năm Báo Thanh Niên",
  "categories": [
    "Video",
    "Giải trí"
  ],
  "sapo": "Nhóm MTV mở màn lễ kỷ niệm 40 năm ngày Báo Thanh Niên ra số báo đầu tiên với ca khúc Thanh Niên Ca.",
  "publishDate": "07/01/2026 14:00 GMT+7",
  "author": {
    "name": "Hữu TínHải Duy",
    "email": ""
  },
  "content": [
    {
      "type": "text",
      "content": "Thanh Niên Ca được nhạc sĩ Võ Thiện Thanh sáng tác, đặc biệt dành tặng cho sự kiện 40 năm Thanh Niên phát hành số báo đầu tiên, cũng như cho đội ngũ những người làm Báo Thanh Niên hôm nay và mai sau. Trên nền nhạc sôi động, hào hùng, chất giọng nội lực của nhóm MTV đã khơi dậy niềm tự hào và dẫn dắt người xem ngược dòng thời gian về những ngày đầu khởi nghiệp."
    },
    {
      "type": "text",
      "content": "Ca từ bài hát gợi nhắc về cột mốc ngày 3.1.1986 - khi tờ báo chính thức ra đời với xuất phát điểm \"3 không\" đầy gian khó: không biên chế, không kinh phí, không trụ sở."
    },
    {
      "type": "text",
      "content": "Từ những thiếu thốn ban đầu đó, các thế hệ người làm báo Thanh Niên đã nối tiếp nhau dấn thân, góp thanh xuân bồi đắp để tờ báo thực hiện cuộc bứt phá ngoạn mục. Đến nay, Thanh Niên đã trở thành một hệ sinh thái truyền thông đa phương tiện hiện đại, giữ vị thế uy tín hàng đầu trong lòng công chúng."
    }
  ],
  "sourceUrl": "https://thanhnien.vn/nhom-mtv-hat-thanh-nien-ca-mung-sinh-nhat-40-nam-bao-thanh-nien-185260106214602229.htm",
  "id": "185260106214602229"
}