{
  "title": "Sân khấu Sen Hồng làm bãi gửi xe máy tuyến metro số 1: Người dân nói gì?",
  "categories": [
    "Video",
    "Thời sự"
  ],
  "sapo": "Sau nhiều năm bỏ hoang, sân khấu Sen Hồng (P.Bến Thành, TP.HCM) sẽ được trưng dụng làm bãi giữ xe máy tạm thời phục vụ hành khách đi tuyến metro số 1, nhằm giảm áp lực cho các bãi xe hiện hữu quanh ga Bến Thành.",
  "publishDate": "10/01/2026 05:31 GMT+7",
  "author": {
    "name": "Chung Phát",
    "avatar": "https://static.thanhnien.com.vn/thanhnien.vn/image/ava_inter.png",
    "email": ""
  },
  "content": [],
  "sourceUrl": "https://thanhnien.vn/san-khau-sen-hong-lam-bai-gui-xe-may-tuyen-metro-so-1-nguoi-dan-noi-gi-185260109154534386.htm",
  "id": "185260109154534386"
}