{
  "title": "Đập phá ô tô vì bị yêu cầu trả phí 'vệ sinh xe'\n    \nĐập phá ô tô vì bị yêu cầu trả phí 'vệ sinh xe'",
  "author": "Hoàng Huy",
  "publishDate": "06/01/2026 20:21 GMT+7\n            \n            \n                06/01/2026 20:21 GMT+7",
  "sapo": "Bực tức vì bị yêu cầu trả phí vệ sinh xe do có người trong nhóm nôn ói, La Thiên Bảo lao vào hành hung tài xế, bẻ gãy gương chiếu hậu ô tô rồi bỏ đi. Công an TP.HCM đã khởi tố Bảo về hành vi \"gây rối trật tự công cộng\".",
  "body": [
    {
      "type": "text",
      "content": "Ngày 6.1, Phòng Cảnh sát hình sự Công an TP.HCM cho biết đã ra quyết định khởi tố vụ án, khởi tố bị can và áp dụng lệnh cấm đi khỏi nơi cư trú đối với La Thiên Bảo (32 tuổi, quê ở tỉnh Đồng Tháp) để điều tra về hành vi 'gây rối trật tự công cộng'."
    },
    {
      "type": "image",
      "url": "https://images2.thanhnien.vn/528068263637045248/2026/1/6/edit-la-thien-bao-1767695672054515430175.jpeg",
      "caption": "Bị can La Thiên Bảo bị khởi tố vì hành hung tài xế, đập phá ô tô"
    },
    {
      "type": "text",
      "content": "Theo hồ sơ vụ việc, tối 13.12.2025, ông N.Q.L (38 tuổi, tài xế xe công nghệ) điều khiển ô tô chở nhóm 6 hành khách (trong đó có Bảo) đi từ đường Lê Văn Khương, phường Tân Thới Hiệp đến đường Phan Văn Trị, phường Hạnh Thông (TP.HCM). Trên đường đi, một người trong nhóm khách do quá chén đã nôn ói ra xe."
    }
  ]
}